Metadata-Version: 2.1
Name: QREDDISH01
Version: 1.0
Summary: TYPE YOUR DESCRIPTION HERE
Home-page: UNKNOWN
Author: YOUR NAME
License: MIT
Platform: UNKNOWN
License-File: LICENSE.txt
